meggie/__init__.py
meggie/configuration.json
meggie/experiment.py
meggie/mainWindowMain.py
meggie/mainWindowUi.py
meggie/run.py
meggie/subject.py
meggie/actions/__init__.py
meggie/actions/epochs_create/__init__.py
meggie/actions/epochs_create/configuration.json
meggie/actions/epochs_create/controller/__init__.py
meggie/actions/epochs_create/controller/epoching.py
meggie/actions/epochs_create/dialogs/__init__.py
meggie/actions/epochs_create/dialogs/createEpochsFromEventsDialogMain.py
meggie/actions/epochs_create/dialogs/createEpochsFromEventsDialogUi.py
meggie/actions/epochs_create/tests/__init__.py
meggie/actions/epochs_create/tests/test_epochs_create.py
meggie/actions/epochs_delete/__init__.py
meggie/actions/epochs_delete/configuration.json
meggie/actions/epochs_delete/tests/__init__.py
meggie/actions/epochs_delete/tests/test_epochs_delete.py
meggie/actions/epochs_delete_from_all/__init__.py
meggie/actions/epochs_delete_from_all/configuration.json
meggie/actions/epochs_delete_from_all/tests/__init__.py
meggie/actions/epochs_delete_from_all/tests/test_epochs_delete_from_all.py
meggie/actions/epochs_info/__init__.py
meggie/actions/epochs_info/configuration.json
meggie/actions/epochs_info/tests/__init__.py
meggie/actions/epochs_info/tests/test_epochs_info.py
meggie/actions/epochs_plot/__init__.py
meggie/actions/epochs_plot/configuration.json
meggie/actions/epochs_plot/tests/__init__.py
meggie/actions/epochs_plot/tests/test_epochs_plot.py
meggie/actions/epochs_plot_image/__init__.py
meggie/actions/epochs_plot_image/configuration.json
meggie/actions/epochs_plot_image/tests/__init__.py
meggie/actions/epochs_plot_image/tests/test_epochs_plot_image.py
meggie/actions/epochs_save/__init__.py
meggie/actions/epochs_save/configuration.json
meggie/actions/epochs_save/controller/epochs.py
meggie/actions/epochs_save/tests/__init__.py
meggie/actions/epochs_save/tests/test_epochs_save_all_channels.py
meggie/actions/epochs_save/tests/test_epochs_save_channel_averages.py
meggie-1.10.0.dist-info/licenses/AUTHORS.rst
meggie-1.10.0.dist-info/licenses/LICENSE
meggie-1.10.0.dist-info/METADATA
meggie-1.10.0.dist-info/WHEEL
meggie-1.10.0.dist-info/entry_points.txt
meggie-1.10.0.dist-info/top_level.txt
meggie-1.10.0.dist-info/RECORD
