Metadata-Version: 2.4
Name: meggie
Version: 1.10.0
Summary: User-friendly graphical user interface to do M/EEG analysis.
License: BSD
Project-URL: homepage, https://github.com/cibr-jyu/meggie
Requires-Python: >=3.10
License-File: LICENSE
License-File: AUTHORS.rst
Requires-Dist: mne~=1.9.0
Requires-Dist: numpy~=2.2.2
Requires-Dist: matplotlib~=3.10.0
Requires-Dist: pandas
Requires-Dist: scikit-learn
Requires-Dist: python-json-logger
Requires-Dist: h5io
Requires-Dist: mne-qt-browser
Requires-Dist: pyqt5
Requires-Dist: appdirs
Requires-Dist: colorama
Provides-Extra: dev
Requires-Dist: black; extra == "dev"
Requires-Dist: pylama; extra == "dev"
Requires-Dist: pytest; extra == "dev"
Requires-Dist: pytest-qt; extra == "dev"
Requires-Dist: build; extra == "dev"
Requires-Dist: twine; extra == "dev"
Requires-Dist: mkdocs; extra == "dev"
Requires-Dist: coverage; extra == "dev"
Requires-Dist: requests; extra == "dev"
Requires-Dist: setuptools; extra == "dev"
Requires-Dist: toml; extra == "dev"
Provides-Extra: test
Requires-Dist: black; extra == "test"
Requires-Dist: pylama; extra == "test"
Requires-Dist: pytest; extra == "test"
Requires-Dist: pytest-qt; extra == "test"
Requires-Dist: setuptools; extra == "test"
Dynamic: license-file
